expand_string/__init__.py
expand_string/__main__.py
expand_string/exceptions.py
expand_string/expand_string.py
expand_string-0.0.2.dist-info/LICENSE
expand_string-0.0.2.dist-info/METADATA
expand_string-0.0.2.dist-info/WHEEL
expand_string-0.0.2.dist-info/top_level.txt
expand_string-0.0.2.dist-info/RECORD
