Metadata-Version: 2.1
Name: expand-string
Version: 0.0.2
Summary: A helper package for expanding strings
Home-page: https://github.com/ja-odur/exapnd-string
Author: J. A. Odur
Author-email: odurjoseph8@gmail.com
License: UNKNOWN
Platform: UNKNOWN
Classifier: Programming Language :: Python :: 3
Classifier: License :: OSI Approved :: MIT License
Classifier: Operating System :: OS Independent
Requires-Python: >=3
